py_to_win_app/__init__.py
py_to_win_app/exceptions.py
py_to_win_app/py_to_win_app.py
py_to_win_app-0.0.2.dist-info/LICENSE
py_to_win_app-0.0.2.dist-info/WHEEL
py_to_win_app-0.0.2.dist-info/METADATA
py_to_win_app-0.0.2.dist-info/RECORD
