Metadata-Version: 2.1
Name: py-to-win-app
Version: 0.0.2
Summary: Make runnable apps from your python scripts!
Home-page: https://github.com/ruslan-rv-ua/py-to-win-app
License: MIT
Author: Ruslan Iskov
Author-email: ruslan.rv.ua@gmail.com
Requires-Python: >=3.9,<4.0
Classifier: License :: OSI Approved :: MIT License
Classifier: Programming Language :: Python :: 3
Classifier: Programming Language :: Python :: 3.10
Classifier: Programming Language :: Python :: 3.9
Requires-Dist: gen-exe (>=0.2.1,<0.3.0)
Requires-Dist: requests (>=2.26.0,<3.0.0)
Requires-Dist: tomli (>=1.2.1,<2.0.0)
Requires-Dist: txtoml (>=1.0.0,<2.0.0)
Project-URL: Documentation, http://ruslan.rv.ua/py-to-win-app/
Project-URL: Repository, https://github.com/ruslan-rv-ua/py-to-win-app
